Jenkinsfile
License.txt
MANIFEST.in
README.rst
setup.py
buildouts/plone4/buildout.cfg
buildouts/plone4/docker-compose.yml
buildouts/plone4/install.sh
buildouts/plone4/versions.cfg
buildouts/plone5/buildout.cfg
buildouts/plone5/docker-compose.yml
buildouts/plone5/install.sh
docs/HISTORY.txt
docs/LICENSE.txt
docs/License.txt
eea/__init__.py
eea.similarity.egg-info/PKG-INFO
eea.similarity.egg-info/SOURCES.txt
eea.similarity.egg-info/dependency_links.txt
eea.similarity.egg-info/entry_points.txt
eea.similarity.egg-info/namespace_packages.txt
eea.similarity.egg-info/not-zip-safe
eea.similarity.egg-info/requires.txt
eea.similarity.egg-info/top_level.txt
eea/similarity/__init__.py
eea/similarity/config.py
eea/similarity/configure.zcml
eea/similarity/interfaces.py
eea/similarity/permissions.zcml
eea/similarity/profiles.zcml
eea/similarity/setuphandlers.py
eea/similarity/similarities.py
eea/similarity/testing.py
eea/similarity/version.txt
eea/similarity/async/__init__.py
eea/similarity/async/configure.zcml
eea/similarity/async/subscribers.py
eea/similarity/browser/__init__.py
eea/similarity/browser/configure.zcml
eea/similarity/browser/img/icon.png
eea/similarity/controlpanel/__init__.py
eea/similarity/controlpanel/configure.zcml
eea/similarity/controlpanel/interfaces.py
eea/similarity/controlpanel/settings.py
eea/similarity/locales/eea.pot
eea/similarity/locales/update.sh
eea/similarity/plugins/__init__.py
eea/similarity/plugins/configure.zcml
eea/similarity/plugins/similaritydialog/README.mkd
eea/similarity/plugins/similaritydialog/css/similarity-dialog.css
eea/similarity/plugins/similaritydialog/js/similarity-dialog.js
eea/similarity/profiles/default/browserlayer.xml
eea/similarity/profiles/default/controlpanel.xml
eea/similarity/profiles/default/cssregistry.xml
eea/similarity/profiles/default/jsregistry.xml
eea/similarity/profiles/default/metadata.xml
eea/similarity/profiles/default/registry.xml
eea/similarity/profiles/default/rolemap.xml
eea/similarity/profiles/uninstall/browserlayer.xml
eea/similarity/profiles/uninstall/controlpanel.xml
eea/similarity/tests/__init__.py
eea/similarity/tests/test_setup.py
eea/similarity/upgrades/__init__.py
eea/similarity/upgrades/configure.zcml